ml_tracking/__init__.py
ml_tracking/ml_tracking.py
ml_tracking-0.0.3.dist-info/LICENSE
ml_tracking-0.0.3.dist-info/METADATA
ml_tracking-0.0.3.dist-info/WHEEL
ml_tracking-0.0.3.dist-info/top_level.txt
ml_tracking-0.0.3.dist-info/RECORD
