Metadata-Version: 2.1
Name: ml-tracking
Version: 0.0.3
Summary: A tracking infrastructure for PatternAg machine learning projects and experiments.
Author-email: Deandra Alvear <deandra@pattern.ag>
Project-URL: Homepage, https://github.com/pttrnag/ds-automation/tree/ml-tracking/ml-tracking
Project-URL: Bug Tracker, https://github.com/pttrnag/ds-automation/tree/ml-tracking/ml-tracking/issues
Classifier: Programming Language :: Python :: 3
Classifier: License :: OSI Approved :: MIT License
Classifier: Operating System :: OS Independent
Requires-Python: >=3.7
License-File: LICENSE
